pyfreerdp-0.0.4.dist-info/top_level.txt
pyfreerdp-0.0.4.dist-info/METADATA
pyfreerdp-0.0.4.dist-info/RECORD
pyfreerdp-0.0.4.dist-info/WHEEL
pyfreerdp/pyfreerdp.abi3.so
pyfreerdp/libpyfreerdp.c
pyfreerdp/bind.c
pyfreerdp/libpyfreerdp.h
pyfreerdp/__init__.py
pyfreerdp.libs/libfreerdp2-b5f98373.so.2.1.1
pyfreerdp.libs/libgpg-error-3f09c3c7.so.0.10.0
pyfreerdp.libs/libelf-0-3d9de92a.176.so
pyfreerdp.libs/libdw-0-780627ce.176.so
pyfreerdp.libs/libicuio-d92a2ee9.so.50.2
pyfreerdp.libs/liblzma-004595ca.so.5.2.2
pyfreerdp.libs/libattr-4f2a9577.so.1.1.0
pyfreerdp.libs/libselinux-0922c95c.so.1
pyfreerdp.libs/libcom_err-2abe824b.so.2.1
pyfreerdp.libs/libgsm-ed01cacd.so.1.0.12
pyfreerdp.libs/libXau-00ec42fe.so.6.0.0
pyfreerdp.libs/libk5crypto-b1f99d5c.so.3.1
pyfreerdp.libs/libwinpr2-733faa64.so.2.1.1
pyfreerdp.libs/libicudata-cb3ba60c.so.50.2
pyfreerdp.libs/libxcb-65da195c.so.1.1.0
pyfreerdp.libs/libkeyutils-dfe70bd6.so.1.5
pyfreerdp.libs/libicui18n-97d01360.so.50.2
pyfreerdp.libs/libkrb5-fcafa220.so.3.3
pyfreerdp.libs/liblz4-af1653fb.so.1.8.3
pyfreerdp.libs/libjpeg-43436dd5.so.62.1.0
pyfreerdp.libs/libpcre-9513aab5.so.1.2.0
pyfreerdp.libs/libxkbfile-bb3d075e.so.1.0.2
pyfreerdp.libs/libgssapi_krb5-497db0c6.so.2.2
pyfreerdp.libs/libicuuc-1796a535.so.50.2
pyfreerdp.libs/libssl-cd1d6220.so.1.0.2k
pyfreerdp.libs/libcrypto-d3570994.so.1.0.2k
pyfreerdp.libs/libsystemd-7fd64813.so.0.6.0
pyfreerdp.libs/libcap-79733b59.so.2.22
pyfreerdp.libs/libX11-9cd84b78.so.6.3.0
pyfreerdp.libs/libkrb5support-d0bcff84.so.0.1
pyfreerdp.libs/libbz2-a273e504.so.1.0.6
pyfreerdp.libs/libgcrypt-18957bae.so.11.8.2
