Metadata-Version: 2.4
Name: pyfreerdp
Version: 0.0.4
Summary: Python wrapper for FreeRDP
Home-page: https://github.com/LeeEirc
Author: Eric
Author-email: Eric <xplzv@126.com>
Classifier: Programming Language :: Python :: 3
Classifier: Programming Language :: Python :: 3.9
Classifier: Programming Language :: Python :: 3.10
Classifier: Programming Language :: Python :: 3.11
Classifier: Programming Language :: Python :: 3.12
Classifier: Programming Language :: Python :: 3.13
Classifier: Programming Language :: C
Classifier: Operating System :: OS Independent
Requires-Python: >=3.9
Dynamic: author
Dynamic: home-page
Dynamic: requires-python
